deepl_tr_pp/__init__.py
deepl_tr_pp/__main__.py
deepl_tr_pp/browse_filename.py
deepl_tr_pp/config.py
deepl_tr_pp/deepl_tr_pp.py
deepl_tr_pp/gen_docx.py
deepl_tr_pp/gen_docx1.py
deepl_tr_pp/gen_filename.py
deepl_tr_pp/load_env.py
deepl_tr_pp/load_text.py
deepl_tr_pp/seg_text.py
deepl_tr_pp-0.1.3.dist-info/entry_points.txt
deepl_tr_pp-0.1.3.dist-info/WHEEL
deepl_tr_pp-0.1.3.dist-info/METADATA
deepl_tr_pp-0.1.3.dist-info/RECORD
