Metadata-Version: 2.1
Name: deepl-tr-pp
Version: 0.1.3
Summary: deepl translate via pyppeteer
Home-page: https://github.com/ffreemt/deepl-tr-pyppeteer
License: MIT
Keywords: mt,language
Author: freemt
Requires-Python: >=3.7,<4.0
Classifier: Environment :: Console
Classifier: License :: OSI Approved :: MIT License
Classifier: Operating System :: OS Independent
Classifier: Programming Language :: Python :: 3
Classifier: Programming Language :: Python :: 3.7
Classifier: Programming Language :: Python :: 3.8
Classifier: Topic :: Software Development :: Libraries :: Python Modules
Requires-Dist: absl-py (>=0.11.0,<0.12.0)
Requires-Dist: cchardet (>=2.1.7,<3.0.0)
Requires-Dist: docx2txt (>=0.8,<0.9)
Requires-Dist: environs (>=9.2.0,<10.0.0)
Requires-Dist: logzero (>=1.6.3,<2.0.0)
Requires-Dist: pydantic (>=1.7.3,<2.0.0)
Requires-Dist: pyperclip (>=1.8.1,<2.0.0)
Requires-Dist: pyppeteer2 (>=0.2.2,<0.3.0)
Requires-Dist: pyquery (>=1.4.3,<2.0.0)
Requires-Dist: python-docx (>=0.8.10,<0.9.0)
Requires-Dist: python-dotenv (>=0.15.0,<0.16.0)
Requires-Dist: tqdm (>=4.56.0,<5.0.0)
Project-URL: Repository, https://github.com/ffreemt/deepl-tr-pyppeteer
